pycricket.py
pycricket_storagehandler.py
py_cricket.egg-info/PKG-INFO
py_cricket.egg-info/SOURCES.txt
py_cricket.egg-info/dependency_links.txt
py_cricket.egg-info/entry_points.txt
py_cricket.egg-info/requires.txt
py_cricket.egg-info/top_level.txt
py_cricket-1.0.11.dist-info/LICENSE
py_cricket-1.0.11.dist-info/METADATA
py_cricket-1.0.11.dist-info/WHEEL
py_cricket-1.0.11.dist-info/entry_points.txt
py_cricket-1.0.11.dist-info/top_level.txt
py_cricket-1.0.11.dist-info/RECORD
