Metadata-Version: 2.1
Name: py-cricket
Version: 1.0.11
Summary: Easy to install and simple way to access all Roanuz Cricket APIs. Its a library 	for showing Live Cricket Score, Cricket Schedule and Statistics
Home-page: https://github.com/roanuz/py-cricket
Author: Roanuz Softwares Private Ltd
Author-email: contact@roanuz.com
License: UNKNOWN
Platform: UNKNOWN
Requires-Dist: requests (>=2.5.1)
